vvallet/__init__.py
vvallet/_base_client.py
vvallet/_client.py
vvallet/_compat.py
vvallet/_constants.py
vvallet/_exceptions.py
vvallet/_files.py
vvallet/_models.py
vvallet/_qs.py
vvallet/_resource.py
vvallet/_response.py
vvallet/_streaming.py
vvallet/_types.py
vvallet/_version.py
vvallet/py.typed
vvallet/_utils/__init__.py
vvallet/_utils/_logs.py
vvallet/_utils/_proxy.py
vvallet/_utils/_reflection.py
vvallet/_utils/_streams.py
vvallet/_utils/_sync.py
vvallet/_utils/_transform.py
vvallet/_utils/_typing.py
vvallet/_utils/_utils.py
vvallet/lib/.keep
vvallet/resources/__init__.py
vvallet/resources/transfer.py
vvallet/resources/wallet.py
vvallet/types/__init__.py
vvallet/types/transfer_create_params.py
vvallet/types/transfer_create_response.py
vvallet/types/wallet_create_address_params.py
vvallet/types/wallet_create_address_response.py
vvallet/types/wallet_create_params.py
vvallet/types/wallet_create_response.py
vvallet/types/wallet_list_addresses_params.py
vvallet/types/wallet_list_addresses_response.py
vvallet/types/wallet_list_balances_params.py
vvallet/types/wallet_list_balances_response.py
vvallet-0.1.0a1.dist-info/METADATA
vvallet-0.1.0a1.dist-info/WHEEL
vvallet-0.1.0a1.dist-info/licenses/LICENSE
vvallet-0.1.0a1.dist-info/RECORD
